MANIFEST.in
Products.PDFtoOCR-configure.zcml
README.txt
setup.cfg
setup.py
Products/__init__.py
Products.PDFtoOCR.egg-info/PKG-INFO
Products.PDFtoOCR.egg-info/SOURCES.txt
Products.PDFtoOCR.egg-info/dependency_links.txt
Products.PDFtoOCR.egg-info/entry_points.txt
Products.PDFtoOCR.egg-info/namespace_packages.txt
Products.PDFtoOCR.egg-info/not-zip-safe
Products.PDFtoOCR.egg-info/requires.txt
Products.PDFtoOCR.egg-info/top_level.txt
Products/PDFtoOCR/__init__.py
Products/PDFtoOCR/configure.zcml
Products/PDFtoOCR/index.py
Products/PDFtoOCR/interfaces.py
Products/PDFtoOCR/profiles.zcml
Products/PDFtoOCR/setuphandlers.py
Products/PDFtoOCR/version.txt
Products/PDFtoOCR/actions/__init__.py
Products/PDFtoOCR/actions/configure.zcml
Products/PDFtoOCR/actions/ocr.py
Products/PDFtoOCR/browser/__init__.py
Products/PDFtoOCR/browser/configure.zcml
Products/PDFtoOCR/browser/do_index.py
Products/PDFtoOCR/browser/status.pt
Products/PDFtoOCR/browser/textfromocr.pt
Products/PDFtoOCR/browser/images/eye-icon.png
Products/PDFtoOCR/profiles/default/Products.PDFtoOCR_various.txt
Products/PDFtoOCR/profiles/default/actionicons.xml
Products/PDFtoOCR/profiles/default/actions.xml
Products/PDFtoOCR/profiles/default/controlpanel.xml
Products/PDFtoOCR/profiles/default/import_steps.xml
Products/PDFtoOCR/profiles/default/metadata.xml
Products/PDFtoOCR/subtypes/__init__.py
Products/PDFtoOCR/subtypes/file.py
Products/PDFtoOCR/tests/__init__.py
Products/PDFtoOCR/tests/base.py
Products/PDFtoOCR/tests/pdftoocr.txt
Products/PDFtoOCR/tests/test_setup.py
docs/HISTORY.txt
docs/INSTALL.txt
docs/LICENSE.GPL
docs/LICENSE.txt