Metadata-Version: 1.0
Name: Products.PDFtoOCR
Version: 1.1
Summary: PDFtoOCR does OCR processing on PDF documents. The text from OCR is used in the search results.
Home-page: http://svn.plone.org/svn/collective/
Author: Plone Collective
Author-email: product-developers@lists.plone.org
License: GPL
Keywords: web zope plone theme
Platform: UNKNOWN
Classifier: Framework :: Plone
Classifier: Programming Language :: Python
Classifier: Topic :: Software Development :: Libraries :: Python Modules
